ec_portal_gun/__init__.py
ec_portal_gun/__main__.py
ec_portal_gun/main.py
ec_portal_gun-0.2.0.dist-info/METADATA
ec_portal_gun-0.2.0.dist-info/WHEEL
ec_portal_gun-0.2.0.dist-info/entry_points.txt
ec_portal_gun-0.2.0.dist-info/RECORD
