Metadata-Version: 2.1
Name: ec-portal-gun
Version: 0.2.0
Summary: 
Author: pysleuth
Author-email: pysleuth@gmail.com
Requires-Python: >=3.10,<4.0
Classifier: Programming Language :: Python :: 3
Classifier: Programming Language :: Python :: 3.10
Classifier: Programming Language :: Python :: 3.11
Classifier: Programming Language :: Python :: 3.12
Requires-Dist: typer[all] (>=0.12.3,<0.13.0)
